icdmap/__init__.py
icdmap/cli.py
icdmap/death_mapper.py
icdmap/mapper.py
icdmap/data/death_cause_mapping.db
icdmap/data/icd_mapping.db
icdmap-0.1.1.dist-info/licenses/LICENSE
icdmap-0.1.1.dist-info/METADATA
icdmap-0.1.1.dist-info/WHEEL
icdmap-0.1.1.dist-info/entry_points.txt
icdmap-0.1.1.dist-info/top_level.txt
icdmap-0.1.1.dist-info/RECORD
