Metadata-Version: 2.4
Name: icdmap
Version: 0.1.1
Summary: Offline ICD-9 and ICD-10 code mapping using SQLite
Author-email: Yong-Zhen Huang <m946111005@tmu.edu.tw>
License-Expression: MIT
Project-URL: Homepage, https://github.com/Brritany/ICDMAP
Project-URL: Source, https://github.com/Brritany/ICDMAP
Project-URL: Tracker, https://github.com/Brritany/ICDMAP/issues
Requires-Python: >=3.7
License-File: LICENSE
Requires-Dist: pandas
Requires-Dist: tqdm
Dynamic: license-file
